Workbook

Sheet Historical Trends
A1: license_start_year | B1: license_count | D1: =export_yearly_trends[[#Headers],[license_start_year]] -> license_start_year | E1: =export_yearly_trends[[#Headers],[license_count]] -> license_count
A2: 1900 | B2: 2 | D2: 2000 | E2: 134
A3: 1910 | B3: 1 | D3: 2001 | E3: 131
A4: 1941 | B4: 1 | D4: 2002 | E4: 152
A5: 1942 | B5: 1 | D5: 2003 | E5: 176
A6: 1944 | B6: 1 | D6: 2004 | E6: 170
A7: 1946 | B7: 1 | D7: 2005 | E7: 173
A8: 1949 | B8: 1 | D8: 2006 | E8: 183
A9: 1950 | B9: 1 | D9: 2007 | E9: 245
A10: 1953 | B10: 1 | D10: 2008 | E10: 275
A11: 1954 | B11: 2 | D11: 2009 | E11: 314
A12: 1955 | B12: 1 | D12: 2010 | E12: 232
A13: 1957 | B13: 1 | D13: 2011 | E13: 262
... A28: 1972 | B28: 6 | D28: 2026 | E28: 695
A29: 1973 | B29: 9
A30: 1974 | B30: 8
A31: 1975 | B31: 8
A32: 1976 | B32: 16
A33: 1977 | B33: 11
A34: 1978 | B34: 13
A35: 1979 | B35: 7
A36: 1980 | B36: 17
A37: 1981 | B37: 16
A38: 1982 | B38: 28
A39: 1983 | B39: 29
A40: 1984 | B40: 40
... A82: 2026 | B82: 695

Sheet Industry Analysis
A1: naics_description | B1: license_count | C1: share_of_total
A2: Lessors of Residential Buildings and Dwellings | B2: 540 | C2: 4.19
A3: All Other Personal Services | B3: 461 | C3: 3.57
A4: Taxi and Ridesharing Services | B4: 418 | C4: 3.24
A5: All Other Transit and Ground Passenger Transportation | B5: 380 | C5: 2.95
A6: Offices of Mental Health Practitioners (except Physicians) | B6: 335 | C6: 2.6
A7: All Other Traveler Accommodation | B7: 329 | C7: 2.55
A8: Independent Artists, Writers, and Performers | B8: 284 | C8: 2.2
A9: All Other Miscellaneous Retailers | B9: 254 | C9: 1.97
A10: Administrative Management and General Management Consulting Services | B10: 246 | C10: 1.91
A11: Residential Remodelers | B11: 243 | C11: 1.88
A12: All Other Professional, Scientific, and Technical Services | B12: 239 | C12: 1.85
A13: Limited-Service Restaurants | B13: 204 | C13: 1.58
... A632: Direct Health and Medical Insurance Carriers | B632: 1 | C632: 0.01

Sheet Ownership Analysis
A1: ownership_type | B1: license_count | C1: share_of_total
A2: Sole proprietorship | B2: 3283 | C2: 25.46
A3: Corporation | B3: 3099 | C3: 24.03
A4: LLC - Single Member | B4: 2797 | C4: 21.69
A5: LLC - Multi Member | B5: 2622 | C5: 20.33
A6: Other | B6: 435 | C6: 3.37
A7: Non Profit Corporation | B7: 137 | C7: 1.06
A8: Association | B8: 109 | C8: 0.85
A9: Limited Liability Limited Ptrs | B9: 108 | C9: 0.84
A10: Professional Association | B10: 98 | C10: 0.76
A11: Limited Liability Ptrs LLP | B11: 88 | C11: 0.68
A12: General Partnership | B12: 87 | C12: 0.67
A13: Limited Partnership | B13: 20 | C13: 0.16
... A18: Tribal Government | B18: 1 | C18: 0.01

Sheet Age Groups
A1: business_age_group | B1: license_count
A2: 1–5 years | B2: 3961
A3: 11–20 years | B3: 2901
A4: 6–10 years | B4: 2678
A5: More than 20 years | B5: 2282
A6: Less than 1 year | B6: 1054
A7: Future start date | B7: 21

Sheet Geographic Analysis
A1: zip_5 | B1: license_count | C1: share_of_seattle_records
A2: 98103 | B2: 688 | C2: 7.81
A3: 98101 | B3: 529 | C3: 6.01
A4: 98118 | B4: 513 | C4: 5.83
A5: 98109 | B5: 471 | C5: 5.35
A6: 98107 | B6: 465 | C6: 5.28
A7: 98122 | B7: 460 | C7: 5.22
A8: 98115 | B8: 438 | C8: 4.97
A9: 98108 | B9: 373 | C9: 4.24
A10: 98104 | B10: 366 | C10: 4.16
A11: 98144 | B11: 364 | C11: 4.13
A12: 98117 | B12: 359 | C12: 4.08
A13: 98125 | B13: 337 | C13: 3.83
... A54: 98160 | B54: 1 | C54: 0.01

Sheet KPI Summary
A1: total_license_records | B1: unique_ubi_count | C1: seattle_address_records | D1: seattle_address_share | E1: average_business_age | F1: started_within_last_5_years | G1: future_dated_records
A2: 12897 | B2: 11659 | C2: 8805 | D2: 68.27 | E2: 11.31 | F2: 5015 | G2: 21
A4: Metric | B4: Value
A5: Total License Records | B5: {=export_kpis[total_license_records]} -> 12897
A6: Unique Businesses (UBI) | B6: {=export_kpis[unique_ubi_count]} -> 11659
A7: Seattle Address Records | B7: {=export_kpis[seattle_address_records]} -> 8805
A8: Seattle Address Share | B8: {=export_kpis[seattle_address_share]/100} -> 0.6827
A9: Average Business Age | B9: {=export_kpis[average_business_age]} -> 11.31
A10: Started Within Last 5 Years | B10: {=export_kpis[started_within_last_5_years]} -> 5015
A11: Future-Dated Records | B11: {=export_kpis[future_dated_records]} -> 21

Sheet Data Validation
A1: Check | B1: SQL Expected | C1: Excel Result | D1: Status
A2: Total License Records | B2: 12897 | C2: ='KPI Summary'!B5 -> 12897 | D2: =IF(B2=C2,"Match","Check") -> Match
A3: Unique UBIs | B3: 11659 | C3: ='KPI Summary'!B6 -> 11659 | D3: =IF(B3=C3,"Match","Check") -> Match
A4: Seattle Address Records | B4: 8805 | C4: ='KPI Summary'!B7 -> 8805 | D4: =IF(B4=C4,"Match","Check") -> Match
A5: Started Within Last 5 Years | B5: 5015 | C5: ='KPI Summary'!B10 -> 5015 | D5: =IF(B5=C5,"Match","Check") -> Match
A6: Future-Dated Records | B6: 21 | C6: ='KPI Summary'!B11 -> 21 | D6: =IF(B6=C6,"Match","Check") -> Match
A7: Age Group Total | B7: 12897 | C7: =SUM('Age Groups'!B2:B7) -> 12897 | D7: =IF(B7=C7,"Match","Check") -> Match

Sheet Analysis Data
A1: business_legal_name | B1: trade_name | C1: ownership_type | D1: naics_code | E1: naics_description | F1: naics_sector | G1: license_start_date | H1: license_start_year | I1: business_age_years | J1: business_age_group | K1: is_future_start_date | L1: street_address | M1: city | N1: state | O1: zip_5 | P1: is_seattle_address | Q1: city_account_number | R1: ubi
A2: ABDURAKHMANOV RASUL | B2: RASUL ABDURAKHMANOV | C2: Sole proprietorship | D2: 485320 | E2: Limousine Service | F2: 48 | G2: 41865 | H2: 2014 | I2: 11 | J2: 11–20 years | K2: 0 | L2: 706 UNION ST # 409 | M2: SEATTLE | N2: WA | O2: 98101 | P2: 1 | Q2: 7748490686809
A3: AHMED MUSTAFE F | B3: MUSTAFE F AHMED | C3: Sole proprietorship | D3: 485999 | E3: All Other Transit and Ground Passenger Transportation | F3: 48 | G3: 41950 | H3: 2014 | I3: 11 | J3: 11–20 years | K3: 0 | L3: 14203 42ND AVE S # 221 | M3: TUKWILA | N3: WA | O3: 98168 | P3: 0 | Q3: 7760940688081
A4: BUI PHUONG | B4: BUI PHUONG | C4: Sole proprietorship | D4: 721191 | E4: Bed-and-Breakfast Inns | F4: 72 | G4: 43704 | H4: 2019 | I4: 6 | J4: 6–10 years | K4: 0 | L4: 2324 1ST AVE #313 | M4: SEATTLE | N4: WA | O4: 98121 | P4: 1 | Q4: 8410320755821 | R4: 6.0449957e+15
A5: CRUZ BRENDAN J | B5: PHENOMENAL PHILLIE | C5: Sole proprietorship | D5: 311811 | E5: Retail Bakeries | F5: 31 | G5: 44774 | H5: 2022 | I5: 4 | J5: 1–5 years | K5: 0 | L5: 4130 PALATINE AVE N | M5: SEATTLE | N5: WA | O5: 98103 | P5: 1 | Q5: 8621920778133 | R5: 604913720
A6: DAVID ANTHONY LEWIS PS | B6: DAVID ANTHONY LEWIS PS | C6: Corporation | D6: 611699 | E6: All Other Miscellaneous Schools and Instruction | F6: 61 | G6: 44595 | H6: 2022 | I6: 4 | J6: 1–5 years | K6: 0 | L6: 8707 16TH AVE SW | M6: SEATTLE | N6: WA | O6: 98106 | P6: 1 | Q6: 8590290774829 | R6: 6.0350592e+15
A7: GATES FOUNDATION TRUST | B7: GATES FOUNDATION TRUST | C7: Other | D7: 813211 | E7: Grantmaking Foundations | F7: 81 | G7: 36526 | H7: 2000 | I7: 26 | J7: More than 20 years | K7: 0 | L7: 500 5TH AVE N | M7: SEATTLE | N7: WA | O7: 98109 | P7: 1 | Q7: 5329790536018 | R7: 6.0159714e+15
A8: INDERJIT TAXI | B8: INDERJIT TAXI | C8: Sole proprietorship | D8: 485310 | E8: Taxi and Ridesharing Services | F8: 48 | G8: 45868 | H8: 2025 | I8: 1 | J8: 1–5 years | K8: 0 | L8: 2464 S 296TH PL | M8: FEDERAL WAY | N8: WA | O8: 98003 | P8: 0 | Q8: 8853030802536
A9: JUGRAJ BRAR | B9: JUGRAJ BRAR | C9: Sole proprietorship | D9: 485999 | E9: All Other Transit and Ground Passenger Transportation | F9: 48 | G9: 41983 | H9: 2014 | I9: 11 | J9: 11–20 years | K9: 0 | L9: 30036 65TH AVE S | M9: AUBURN | N9: WA | O9: 98001 | P9: 0 | Q9: 7777700689807 | R9: 7777700689807
A10: LYKKEN JOSEPH ALAN | B10: JOSEPH A LYKKEN | C10: Sole proprietorship | D10: 721191 | E10: Bed-and-Breakfast Inns | F10: 72 | G10: 43814 | H10: 2019 | I10: 6 | J10: 6–10 years | K10: 0 | L10: 519 32ND AVE E | M10: SEATTLE | N10: WA | O10: 98112 | P10: 1 | Q10: 8439890758892 | R10: 6.0452344e+15
A11: MANGASTO ZERFE W | B11: MANGSTO ZERFE | C11: Sole proprietorship | D11: 485320 | E11: Limousine Service | F11: 48 | G11: 42144 | H11: 2015 | I11: 11 | J11: 11–20 years | K11: 0 | L11: 17210 30TH AVE S # H11 | M11: SEATAC | N11: WA | O11: 98188 | P11: 0 | Q11: 7833790695669
A12: MERKEL JR JOEL C & REYNEVELD SARAH | B12: MERKEL JR JOEL C | C12: Sole proprietorship | D12: 721191 | E12: Bed-and-Breakfast Inns | F12: 72 | G12: 42644 | H12: 2016 | I12: 9 | J12: 6–10 years | K12: 0 | L12: 7353 16TH AVE NW | M12: SEATTLE | N12: WA | O12: 98117 | P12: 1 | Q12: 8370590751644 | R12: 6.0428551e+15
A13: MOTS LLC | B13: LOAD RUNNER | C13: LLC - Single Member | D13: 812990 | E13: All Other Personal Services | F13: 81 | G13: 44126 | H13: 2020 | I13: 5 | J13: 1–5 years | K13: 0 | L13: 1012 S HENDERSON ST # B | M13: SEATTLE | N13: WA | O13: 98108 | P13: 1 | Q13: 8503350765696 | R13: 6.0429548e+15
A14: PERKINS EASTMAN ARCHITECTS DPC | B14: PERKINS EASTMAN ARCHITECTS DPC | C14: Corporation | D14: 541310 | E14: Architectural Services | F14: 54 | G14: 41275 | H14: 2013 | I14: 13 | J14: 11–20 years | K14: 0 | L14: 115 5TH AVE # 3 | M14: NEW YORK | N14: NY | O14: 10003 | P14: 0 | Q14: 8360110750546 | R14: 6.032434e+15
A15: PLANET WISE SOLUTIONS | B15: PLANET WISE SOLUTIONS | C15: Association | D15: 812990 | E15: All Other Personal Services | F15: 81 | G15: 39545 | H15: 2008 | I15: 18 | J15: 11–20 years | K15: 0 | L15: 13714 37TH AVE NE | M15: SEATTLE | N15: WA | O15: 98125 | P15: 1 | Q15: 7069140614696 | R15: 6.0282056e+15
A16: ROOTED RITUAL SALON LLC | B16: ROOTED RITUAL SALON | C16: LLC - Single Member | D16: 812112 | E16: Beauty Salons | F16: 81 | G16: 43157 | H16: 2018 | I16: 8 | J16: 6–10 years | K16: 0 | L16: 1416 NW BALLARD WAY | M16: SEATTLE | N16: WA | O16: 98107 | P16: 1 | Q16: 8185690732262 | R16: 6.0420011e+15
A17: SCHNITZER PROPERTIES MANAGEMENT LLC | B17: HARSCH INVESTMENT PROPERTIES MANAGEMENT LLC | C17: LLC - Multi Member | D17: 531210 | E17: Offices of Real Estate Agents and Brokers | F17: 53 | G17: 37074 | H17: 2001 | I17: 25 | J17: More than 20 years | K17: 0 | L17: 309 S CLOVERDALE ST # B14 | M17: SEATTLE | N17: WA | O17: 98108 | P17: 1 | Q17: 5515700555922 | R17: 6.0213351e+15
A18: THIND MANJIT SINGH | B18: MANJIT SINGH THIND | C18: Sole proprietorship | D18: 485999 | E18: All Other Transit and Ground Passenger Transportation | F18: 48 | G18: 41981 | H18: 2014 | I18: 11 | J18: 11–20 years | K18: 0 | L18: 13229 SE 234TH ST | M18: KENT | N18: WA | O18: 98042 | P18: 0 | Q18: 7776510689683
A19: VERDANT COMMERCIAL CAPITAL LLC | B19: VERDANT COMMERCIAL CAPITAL LLC | C19: LLC - Single Member | D19: 532420 | E19: Office Machinery and Equipment Rental and Leasing | F19: 53 | G19: 43101 | H19: 2018 | I19: 8 | J19: 6–10 years | K19: 0 | L19: 9987 CARVER RD # 110 | M19: CINCINNATI | N19: OH | O19: 45242 | P19: 0 | Q19: 8829560800100 | R19: 6.0430759e+15
A20: #1 SEATTLE LUXURY ADULT FAMILY HOME | B20: SEATTLE LUXURY ADULT FAMILY HOME | C20: LLC - Multi Member | D20: 623990 | E20: Other Residential Care Facilities | F20: 62 | G20: 45839 | H20: 2025 | I20: 1 | J20: 1–5 years | K20: 0 | L20: 10006 SAND POINT WAY NE | M20: SEATTLE | N20: WA | O20: 98125 | P20: 1 | Q20: 8831440800297 | R20: 6.056395e+15
A21: 0 BLOK LLC | B21: 0BLOK | C21: LLC - Single Member | D21: 541310 | E21: Architectural Services | F21: 54 | G21: 44405 | H21: 2021 | I21: 5 | J21: 1–5 years | K21: 0 | L21: 515 29TH AVE S | M21: SEATTLE | N21: WA | O21: 98144 | P21: 1 | Q21: 8551870770776 | R21: 6.0476766e+15
A22: 002 LIMA LLC | B22: 002 LIMA LLC | C22: LLC - Single Member | D22: 531110 | E22: Lessors of Residential Buildings and Dwellings | F22: 53 | G22: 45061 | H22: 2023 | I22: 3 | J22: 1–5 years | K22: 0 | L22: 4515C SUNNYSIDE AVE N | M22: SEATTLE | N22: WA | O22: 98103 | P22: 1 | Q22: 8683360784544 | R22: 6.050156e+15
A23: 003 LLC | B23: 003 LLC | C23: LLC - Multi Member | D23: 561320 | E23: Temporary Help Services | F23: 56 | G23: 42186 | H23: 2015 | I23: 11 | J23: 11–20 years | K23: 0 | L23: 1500 WESTLAKE AVE N # 212 | M23: SEATTLE | N23: WA | O23: 98109 | P23: 1 | Q23: 7861530698534 | R23: 6.0313493e+15
A24: 080 NETWORKS | B24: 080NETWORKS | C24: LLC - Multi Member | D24: 541511 | E24: Custom Computer Programming Services | F24: 54 | G24: 39680 | H24: 2008 | I24: 17 | J24: 11–20 years | K24: 0 | L24: 1676 NORTHLAKE WAY NW | M24: BREMERTON | N24: WA | O24: 98312 | P24: 0 | Q24: 7111560619170 | R24: 6.028583e+15
A25: 0982563 BC LTD | B25: SURGE PRODUCTIONS | C25: Corporation | D25: 711320 | E25: Promoters of Performing Arts, Sports, and Similar Events without Facilities | F25: 71 | G25: 42741 | H25: 2017 | I25: 9 | J25: 6–10 years | K25: 0 | L25: 101 215 OSWEGO ST | M25: VICTORIA | N25: BC | O25: V8V 2 | P25: 0 | Q25: 8356270750132 | R25: 6.0407742e+15
A26: 1 AD STUDIO | B26: 1 AD STUDIO | C26: LLC - Multi Member | D26: 541410 | E26: Interior Design Services | F26: 54 | G26: 42089 | H26: 2015 | I26: 11 | J26: 11–20 years | K26: 0 | L26: 3270 41ST AVE SW | M26: SEATTLE | N26: WA | O26: 98116 | P26: 1 | Q26: 7817000693916 | R26: 6.0349199e+15
A27: 1 FINE AUTO LLC | B27: RICHS CUSTOM UPHOLSTERY | C27: LLC - Multi Member | D27: 811121 | E27: Automotive Body, Paint, and Interior Repair and Maintenance | F27: 81 | G27: 39904 | H27: 2009 | I27: 17 | J27: 11–20 years | K27: 0 | L27: 10003 AURORA AVE N | M27: SEATTLE | N27: WA | O27: 98133 | P27: 1 | Q27: 7173520625939 | R27: 6.0290209e+15
A28: 1 LIFE CONSTRUCTION INC | B28: PIPE DR & AFFORDABLE SEWER & DRAIN | C28: Corporation | D28: 236118 | E28: Residential Remodelers | F28: 23 | G28: 41821 | H28: 2014 | I28: 12 | J28: 11–20 years | K28: 0 | L28: 12345 LAKE CITY WAY NE # 311 | M28: SEATTLE | N28: WA | O28: 98125 | P28: 1 | Q28: 7895510702061 | R28: 6.0342172e+15
A29: 1 NEW MECHANICAL LLC | B29: 1 NEW MECHANICAL LLC | C29: LLC - Single Member | D29: 238220 | E29: Plumbing, Heating, and Air-Conditioning Contractors | F29: 23 | G29: 43776 | H29: 2019 | I29: 6 | J29: 6–10 years | K29: 0 | L29: 11906 206TH AVE SE | M29: SNOHOMISH | N29: WA | O29: 98290 | P29: 0 | Q29: 8430560757910 | R29: 6.0409739e+15
A30: 1 PRO NAILS LLC | B30: 1 PRO NAILS | C30: LLC - Multi Member | D30: 812112 | E30: Beauty Salons | F30: 81 | G30: 37622 | H30: 2003 | I30: 23 | J30: More than 20 years | K30: 0 | L30: 18 ROY ST | M30: SEATTLE | N30: WA | O30: 98109 | P30: 1 | Q30: 5574740562230 | R30: 6.0225133e+15
... A154: 1556 NW 62ND STREET LLC | B154: 1556 NW 62ND STREET LLC | C154: LLC - Single Member | D154: 531110 | E154: Lessors of Residential Buildings and Dwellings | F154: 53 | G154: 45383 | H154: 2024 | I154: 2 | J154: 1–5 years | K154: 0 | L154: 330 ARIA LN | M154: WENATCHEE | N154: WA | O154: 98801 | P154: 0 | Q154: 8745500791145 | R154: 6.0543129e+15
A155: 1560 RENTAL | B155: KEVIN BURTCHAELL | C155: Sole proprietorship | D155: 721191 | E155: Bed-and-Breakfast Inns | F155: 72 | G155: 45272 | H155: 2023 | I155: 2 | J155: 1–5 years | K155: 0 | L155: 1560 NE 106TH ST | M155: SEATTLE | N155: WA | O155: 98125 | P155: 1 | Q155: 8726750789189
A156: 15TH AVE EAST MERCHANTS ASSOC | B156: 15TH AVE EAST MERCHANTS ASSOC | C156: Association | D156: 813910 | E156: Business Associations | F156: 81 | G156: 44537 | H156: 2021 | I156: 4 | J156: 1–5 years | K156: 0 | L156: 425 15TH AVE E | M156: SEATTLE | N156: WA | O156: 98112 | P156: 1 | Q156: 8662020782342 | R156: 6.0331797e+15
A157: 15TH STREET VINTAGE | B157: 15TH STREET VINTAGE | C157: Corporation | D157: 459510 | E157: Used Merchandise Retailers | F157: 45 | G157: 45383 | H157: 2024 | I157: 2 | J157: 1–5 years | K157: 0 | L157: 7346 15TH AVE NW | M157: SEATTLE | N157: WA | O157: 98117 | P157: 1 | Q157: 8750440791708 | R157: 6.0538627e+15
A158: 16 RAVENNA LLC | B158: 16 RAVENNA LLC | C158: LLC - Single Member | D158: 721191 | E158: Bed-and-Breakfast Inns | F158: 72 | G158: 45870 | H158: 2025 | I158: 1 | J158: 1–5 years | K158: 0 | L158: 522 W RIVERSIDE AVE | M158: SPOKANE | N158: WA | O158: 99201 | P158: 0 | Q158: 8877430805096 | R158: 6.0594872e+15
A159: 16 VISIONS LLC | B159: 16 VISIONS LLC | C159: LLC - Multi Member | D159: 513199 | E159: All Other Publishers | F159: 51 | G159: 37257 | H159: 2002 | I159: 24 | J159: More than 20 years | K159: 0 | L159: 1106 18TH AVE | M159: SEATTLE | N159: WA | O159: 98122 | P159: 1 | Q159: 5526650557086 | R159: 6.0216465e+15
A160: 1601 DEXTER AVE N SEA LLC | B160: LAKE UNION EATS | C160: LLC - Single Member | D160: 531190 | E160: Lessors of Other Real Estate Property | F160: 53 | G160: 44838 | H160: 2022 | I160: 3 | J160: 1–5 years | K160: 0 | L160: 1601 DEXTER AVE N | M160: SEATTLE | N160: WA | O160: 98109 | P160: 1 | Q160: 8758370792535 | R160: 6.0471768e+15
A161: 1608 LLC | B161: THE ATTIC | C161: LLC - Multi Member | D161: 722511 | E161: Full-Service Restaurants | F161: 72 | G161: 45019 | H161: 2023 | I161: 3 | J161: 1–5 years | K161: 0 | L161: 4226 E MADISON ST | M161: SEATTLE | N161: WA | O161: 98112 | P161: 1 | Q161: 8670220783183 | R161: 6.049858e+15
A162: 1611 HOLDINGS GROUP LLC | B162: 1611 HOLDINGS GROUP | C162: LLC - Multi Member | D162: 541611 | E162: Administrative Management and General Management Consulting Services | F162: 54 | G162: 42552 | H162: 2016 | I162: 10 | J162: 6–10 years | K162: 0 | L162: 1611 10TH AVE W | M162: SEATTLE | N162: WA | O162: 98119 | P162: 1 | Q162: 7987870711674 | R162: 6.0400235e+15
A163: 1613 5TH AVE W STR | B163: 1613 5TH AVE W STR | C163: Sole proprietorship | D163: 721191 | E163: Bed-and-Breakfast Inns | F163: 72 | G163: 46148 | H163: 2026 | I163: 0 | J163: Less than 1 year | K163: 0 | L163: 1613 5TH AVE W | M163: SEATTLE | N163: WA | O163: 98119 | P163: 1 | Q163: 8921040809794
A164: 1621 S STATE ST LLC | B164: 1621 S STATE ST LLC | C164: LLC - Single Member | D164: 531311 | E164: Residential Property Managers | F164: 53 | G164: 45756 | H164: 2025 | I164: 1 | J164: 1–5 years | K164: 0 | L164: 1621 S STATE ST | M164: SEATTLE | N164: WA | O164: 98144 | P164: 1 | Q164: 8829260800067 | R164: 6.058403e+15
A165: 1646SKINGSEATTLE LLC | B165: 1646SKINGSEATTLE LLC | C165: Other | D165: 531390 | E165: Other Activities Related to Real Estate | F165: 53 | G165: 43697 | H165: 2019 | I165: 6 | J165: 6–10 years | K165: 0 | L165: 1646 S KING ST | M165: SEATTLE | N165: WA | O165: 98144 | P165: 1 | Q165: 8402540754991 | R165: 6.0450575e+15
A166: 168 KITCHEN & BATH CORP | B166: 168 KITCHEN & BATH CORP | C166: Corporation | D166: 236118 | E166: Residential Remodelers | F166: 23 | G166: 45139 | H166: 2023 | I166: 3 | J166: 1–5 years | K166: 0 | L166: 5133 S AVON ST | M166: SEATTLE | N166: WA | O166: 98178 | P166: 1 | Q166: 8698450786160 | R166: 6.0528155e+15
A167: 16D LLC | B167: 16D LLC | C167: LLC - Multi Member | D167: 236115 | E167: New Single-Family Housing Construction (except For-Sale Builders) | F167: 23 | G167: 40627 | H167: 2011 | I167: 15 | J167: 11–20 years | K167: 0 | L167: 10602 SW 110TH ST | M167: VASHON | N167: WA | O167: 98070 | P167: 0 | Q167: 7385140648547 | R167: 6.0309252e+15
A168: 16TH & CHERRY LLC | B168: CC APARTMENTS | C168: LLC - Multi Member | D168: 531311 | E168: Residential Property Managers | F168: 53 | G168: 44043 | H168: 2020 | I168: 6 | J168: 6–10 years | K168: 0 | L168: 701 16TH AVE | M168: SEATTLE | N168: WA | O168: 98122 | P168: 1 | Q168: 8505570765943 | R168: 6.0268681e+15
A169: 16TH WORKSHOP INC | B169: 16TH WORKSHOP | C169: Corporation | D169: 337122 | E169: Nonupholstered Wood Household Furniture Manufacturing | F169: 33 | G169: 39692 | H169: 2008 | I169: 17 | J169: 11–20 years | K169: 0 | L169: 1802 S DEARBORN ST | M169: SEATTLE | N169: WA | O169: 98144 | P169: 1 | Q169: 7110970619105 | R169: 6.0285595e+15
A170: 17 BIT INC | B170: 17 BIT INC | C170: Corporation | D170: 541511 | E170: Custom Computer Programming Services | F170: 54 | G170: 40359 | H170: 2010 | I170: 16 | J170: 11–20 years | K170: 0 | L170: 5728 S RYAN ST | M170: SEATTLE | N170: WA | O170: 98178 | P170: 1 | Q170: 7404140650534 | R170: 6.0302896e+15
A171: 17 KNOTS LLC | B171: 17 KNOTS CONSULTING | C171: LLC - Single Member | D171: 541219 | E171: Other Accounting Services | F171: 54 | G171: 45986 | H171: 2025 | I171: 0 | J171: Less than 1 year | K171: 0 | L171: 1914 N 120TH ST | M171: SEATTLE | N171: WA | O171: 98133 | P171: 1 | Q171: 8901440807758 | R171: 6.060039e+15
A172: 1716 N 46TH ST A DELAWARE LLC | B172: NELSON RENTALS | C172: LLC - Multi Member | D172: 531110 | E172: Lessors of Residential Buildings and Dwellings | F172: 53 | G172: 45885 | H172: 2025 | I172: 0 | J172: Less than 1 year | K172: 0 | L172: 1716 N 46TH ST | M172: SEATTLE | N172: WA | O172: 98103 | P172: 1 | Q172: 8864640803733 | R172: 6.0596634e+15
A173: 1716 RENTAL LLC | B173: 1716 RENTAL | C173: LLC - Single Member | D173: 531110 | E173: Lessors of Residential Buildings and Dwellings | F173: 53 | G173: 44562 | H173: 2022 | I173: 4 | J173: 1–5 years | K173: 0 | L173: 1716 NE 58TH ST | M173: SEATTLE | N173: WA | O173: 98105 | P173: 1 | Q173: 8581780773939 | R173: 6.0486121e+15
A174: 1724 MLK LLC | B174: 1724 MLK LLC | C174: LLC - Single Member | D174: 531110 | E174: Lessors of Residential Buildings and Dwellings | F174: 53 | G174: 46174 | H174: 2026 | I174: 0 | J174: Less than 1 year | K174: 0 | L174: 1420 5TH AVE # 3100 | M174: SEATTLE | N174: WA | O174: 98101 | P174: 1 | Q174: 8925100810216 | R174: 6.0621433e+15
A175: 1724 REINVESTMENT LLC | B175: 400 BLAINE APARTMENTS | C175: LLC - Multi Member | D175: 531110 | E175: Lessors of Residential Buildings and Dwellings | F175: 53 | G175: 43983 | H175: 2020 | I175: 6 | J175: 6–10 years | K175: 0 | L175: 400 BLAINE ST | M175: SEATTLE | N175: WA | O175: 98109 | P175: 1 | Q175: 8482200763455 | R175: 6.0260476e+15
... A236: 2020 FINANCIAL PLANNING LLC | B236: 2020 FINANCIAL PLANNING LLC | C236: LLC - Multi Member | D236: 523940 | E236: Portfolio Management and Investment Advice | F236: 52 | G236: 40296 | H236: 2010 | I236: 16 | J236: 11–20 years | K236: 0 | L236: 1700 7TH AVE # 2100 | M236: SEATTLE | N236: WA | O236: 98101 | P236: 1 | Q236: 7284190637717 | R236: 6.0302436e+15
A237: 2020 TEST ACCOUNT | B237: 2020 TEST ACCOUNT | C237: Sole proprietorship | D237: 485999 | E237: All Other Transit and Ground Passenger Transportation | F237: 48 | G237: 43742 | H237: 2019 | I237: 6 | J237: 6–10 years | K237: 0 | L237: 700 5TH AVE | M237: SEATTLE | N237: WA | O237: 98104 | P237: 1 | Q237: 8420170756831
A238: 2020 TEST ACCOUNT | B238: TESTING 2026 OB DUE DATE | C238: Sole proprietorship | D238: 485999 | E238: All Other Transit and Ground Passenger Transportation | F238: 48 | G238: 46296 | H238: 2026 | I238: 0 | J238: Future start date | K238: 1 | L238: 700 5TH AVE | M238: SEATTLE | N238: WA | O238: 98104 | P238: 1 | Q238: 8420170805682
A239: 2020 VISION PAINTING | B239: 2020 VISION PAINTING | C239: LLC - Single Member | D239: 238320 | E239: Painting and Wall Covering Contractors | F239: 23 | G239: 44040 | H239: 2020 | I239: 6 | J239: 6–10 years | K239: 0 | L239: 13715 CORLISS AVE N | M239: SEATTLE | N239: WA | O239: 98133 | P239: 1 | Q239: 8634320779432 | R239: 6.0463207e+15
A240: 2022HY LLC | B240: 2022HY LLC | C240: LLC - Single Member | D240: 531110 | E240: Lessors of Residential Buildings and Dwellings | F240: 53 | G240: 45437 | H240: 2024 | I240: 2 | J240: 1–5 years | K240: 0 | L240: 2022 E REPUBLICAN ST | M240: SEATTLE | N240: WA | O240: 98112 | P240: 1 | Q240: 8762360792957 | R240: 6.0554615e+15
A241: 2024 14TH PROPERTY MGMT LLC | B241: 2024 14TH PROPERTY MGMT LLC | C241: LLC - Single Member | D241: 721199 | E241: All Other Traveler Accommodation | F241: 72 | G241: 45069 | H241: 2023 | I241: 3 | J241: 1–5 years | K241: 0 | L241: 2024 14TH AVE W | M241: SEATTLE | N241: WA | O241: 98119 | P241: 1 | Q241: 8697130786025 | R241: 6.0525732e+15
A242: 203 DEGREES FAHRENHEIT CORP | B242: 203 DEGREES FAHRENHEIT | C242: Corporation | D242: 722515 | E242: Snack and Nonalcoholic Beverage Bars | F242: 72 | G242: 44256 | H242: 2021 | I242: 5 | J242: 1–5 years | K242: 0 | L242: 610 TERRY AVE N # 170 | M242: SEATTLE | N242: WA | O242: 98109 | P242: 1 | Q242: 8876580804992 | R242: 6.0419764e+15
A243: 2032 ENS LLC | B243: 2032 ENS LLC | C243: LLC - Single Member | D243: 531110 | E243: Lessors of Residential Buildings and Dwellings | F243: 53 | G243: 44952 | H243: 2023 | I243: 3 | J243: 1–5 years | K243: 0 | L243: 2032 E NEWTON ST | M243: SEATTLE | N243: WA | O243: 98112 | P243: 1 | Q243: 8661890782329 | R243: 6.0493503e+15
A244: 2051 MADISON STREET PARTNERS LLC | B244: 2051 MADISON STREET PARTNERS LLC | C244: LLC - Multi Member | D244: 531311 | E244: Residential Property Managers | F244: 53 | G244: 44927 | H244: 2023 | I244: 3 | J244: 1–5 years | K244: 0 | L244: 1717 22ND AVE | M244: SEATTLE | N244: WA | O244: 98122 | P244: 1 | Q244: 8692800785572 | R244: 6.033715e+15
A245: 206 DRIVING SCHOOL LLC | B245: 206 DRIVING SCHOOL LLC | C245: LLC - Multi Member | D245: 611692 | E245: Automobile Driving Schools | F245: 61 | G245: 45658 | H245: 2025 | I245: 1 | J245: 1–5 years | K245: 0 | L245: 9040 RAINIER AVE S | M245: SEATTLE | N245: WA | O245: 98118 | P245: 1 | Q245: 8804560797479 | R245: 6.0564827e+15
A246: 206 ELECTRIC LLC | B246: 206 ELECTRIC | C246: LLC - Single Member | D246: 238210 | E246: Electrical Contractors and Other Wiring Installation Contractors | F246: 23 | G246: 45618 | H246: 2024 | I246: 1 | J246: 1–5 years | K246: 0 | L246: 109 198TH ST SE | M246: BOTHELL | N246: WA | O246: 98012 | P246: 0 | Q246: 8798330796798 | R246: 16055013410001
A247: 206 EVENTS | B247: 206 EVENTS | C247: Other | D247: 541990 | E247: All Other Professional, Scientific, and Technical Services | F247: 54 | G247: 43101 | H247: 2018 | I247: 8 | J247: 6–10 years | K247: 0 | L247: 18336 AURORA AVE N # 105 | M247: SHORELINE | N247: WA | O247: 98133 | P247: 0 | Q247: 8285030742709 | R247: 6.0355232e+15
A248: 206 MINI MART | B248: 206 MINI MART | C248: LLC - Single Member | D248: 459999 | E248: All Other Miscellaneous Retailers | F248: 45 | G248: 43971 | H248: 2020 | I248: 6 | J248: 6–10 years | K248: 0 | L248: 8738 RAINIER AVE S | M248: SEATTLE | N248: WA | O248: 98118 | P248: 1 | Q248: 8629640778931 | R248: 6.0460952e+15
A249: 206 NOW LLC | B249: 206 NOW | C249: LLC - Multi Member | D249: 561520 | E249: Tour Operators | F249: 56 | G249: 42860 | H249: 2017 | I249: 9 | J249: 6–10 years | K249: 0 | L249: 1415 2ND AVE # 602 | M249: SEATTLE | N249: WA | O249: 98101 | P249: 1 | Q249: 8075200720771 | R249: 6.0411959e+15
A250: 206 PARTNERS LLC | B250: 206 PARTNERS LLC | C250: Limited Liability Limited Ptrs | D250: 531210 | E250: Offices of Real Estate Agents and Brokers | F250: 53 | G250: 43101 | H250: 2018 | I250: 8 | J250: 6–10 years | K250: 0 | L250: 1225 S WELLER ST #500 | M250: SEATTLE | N250: WA | O250: 98144 | P250: 1 | Q250: 8184810732173 | R250: 6.0420443e+15
... A395: 3 SQUIRRELS BELLTOWN LLC | B395: 3 SQUIRRELS BELLTOWN LLC | C395: LLC - Single Member | D395: 531110 | E395: Lessors of Residential Buildings and Dwellings | F395: 53 | G395: 45901 | H395: 2025 | I395: 0 | J395: Less than 1 year | K395: 0 | L395: 2415 2ND AVE | M395: SEATTLE | N395: WA | O395: 98121 | P395: 1 | Q395: 8852840802517 | R395: 6.058993e+15
A396: 3 WHEEL MOTION | B396: 3 WHEEL MOTION | C396: Sole proprietorship | D396: 459999 | E396: All Other Miscellaneous Retailers | F396: 45 | G396: 45133 | H396: 2023 | I396: 3 | J396: 1–5 years | K396: 0 | L396: 904 OCCIDENTAL AVE S # C | M396: SEATTLE | N396: WA | O396: 98134 | P396: 1 | Q396: 8701010786429
A397: 3 WIRE LLC | B397: 3 WIRE LLC | C397: Other | D397: 811310 | E397: Commercial and Industrial Machinery and Equipment (except Automotive and Electronic) Repair and Maintenance | F397: 81 | G397: 43282 | H397: 2018 | I397: 8 | J397: 6–10 years | K397: 0 | L397: 22310 20TH AVE SE # 200 | M397: BOTHELL | N397: WA | O397: 98021 | P397: 0 | Q397: 8288450743068 | R397: 6.0428299e+15
A398: 300 PINE STREET CONDOMINIUM ASSOCIATION | B398: 300 PINE STREET CONDOMINIUM ASSOCIATION | C398: Association | D398: 531390 | E398: Other Activities Related to Real Estate | F398: 53 | G398: 44287 | H398: 2021 | I398: 5 | J398: 1–5 years | K398: 0 | L398: 300 PINE ST | M398: SEATTLE | N398: WA | O398: 98101 | P398: 1 | Q398: 8577160773434 | R398: 6.0354521e+15
A399: 3004 5TH AVE WEST LLC | B399: 3004 5TH AVE WEST | C399: LLC - Single Member | D399: 531110 | E399: Lessors of Residential Buildings and Dwellings | F399: 53 | G399: 45061 | H399: 2023 | I399: 3 | J399: 1–5 years | K399: 0 | L399: 3004 5TH AVE W | M399: SEATTLE | N399: WA | O399: 98119 | P399: 1 | Q399: 8687120784952 | R399: 6.0523431e+15
A400: 3008 63RD AVE SW LLC | B400: 3008 63RD AVE SW LLC | C400: LLC - Single Member | D400: 531110 | E400: Lessors of Residential Buildings and Dwellings | F400: 53 | G400: 45667 | H400: 2025 | I400: 1 | J400: 1–5 years | K400: 0 | L400: 3225 MCLEOD DR # 100 | M400: LAS VEGAS | N400: NV | O400: 89121 | P400: 0 | Q400: 8801700797146 | R400: 6.0564762e+15
A401: 300DEGREES PLLC | B401: 300DEGREES PLLC | C401: Other | D401: 541110 | E401: Offices of Lawyers | F401: 54 | G401: 43291 | H401: 2018 | I401: 8 | J401: 6–10 years | K401: 0 | L401: 2125 1ST AVE # 1506 | M401: SEATTLE | N401: WA | O401: 98121 | P401: 1 | Q401: 8271500741288 | R401: 6.0429169e+15
A402: 301 WKB LLC | B402: 301 WKB LLC | C402: LLC - Multi Member | D402: 531210 | E402: Offices of Real Estate Agents and Brokers | F402: 53 | G402: 38825 | H402: 2006 | I402: 20 | J402: 11–20 years | K402: 0 | L402: 7724 35TH AVE NE # 15257 | M402: SEATTLE | N402: WA | O402: 98115 | P402: 1 | Q402: 5908810597957 | R402: 6.0259815e+15
A403: 3015 W VIEWMONT WAY W LLC | B403: 3015 W VIEWMONT WAY W LLC | C403: LLC - Multi Member | D403: 531110 | E403: Lessors of Residential Buildings and Dwellings | F403: 53 | G403: 46054 | H403: 2026 | I403: 0 | J403: Less than 1 year | K403: 0 | L403: 3015 W VIEWMONT WAY W | M403: SEATTLE | N403: WA | O403: 98199 | P403: 1 | Q403: 8889970806479 | R403: 6.0603032e+15
A404: 303 NE NORTHLAKE WAY LLC | B404: 303 NE NORTHLAKE WAY LLC | C404: Limited Liability Ptrs LLP | D404: 531120 | E404: Lessors of Nonresidential Buildings (except Miniwarehouses) | F404: 53 | G404: 41796 | H404: 2014 | I404: 12 | J404: 11–20 years | K404: 0 | L404: 303 NE NORTHLAKE WAY | M404: SEATTLE | N404: WA | O404: 98105 | P404: 1 | Q404: 7715740683379 | R404: 6.034045e+15
A405: 3046 13TH AVE W LLC | B405: 3046 13TH AVE W LLC | C405: LLC - Multi Member | D405: 531311 | E405: Residential Property Managers | F405: 53 | G405: 41604 | H405: 2013 | I405: 12 | J405: 11–20 years | K405: 0 | L405: 10318 13TH AVE NW | M405: SEATTLE | N405: WA | O405: 98177 | P405: 1 | Q405: 7632450674662 | R405: 6.0335168e+15
A406: 306 QA LLC | B406: 306 QA | C406: LLC - Multi Member | D406: 531110 | E406: Lessors of Residential Buildings and Dwellings | F406: 53 | G406: 42917 | H406: 2017 | I406: 9 | J406: 6–10 years | K406: 0 | L406: 306 QUEEN ANNE AVE N | M406: SEATTLE | N406: WA | O406: 98109 | P406: 1 | Q406: 8530660768575 | R406: 6.0317054e+15
A407: 307 ON 5TH AVE LLC | B407: 307 ON 5TH AVE LLC | C407: LLC - Multi Member | D407: 531190 | E407: Lessors of Other Real Estate Property | F407: 53 | G407: 42689 | H407: 2016 | I407: 9 | J407: 6–10 years | K407: 0 | L407: 2132 5TH AVE # 307 | M407: SEATTLE | N407: WA | O407: 98121 | P407: 1 | Q407: 8431960758052 | R407: 6.0405751e+15
A408: 310 11TH AVE E LLC | B408: 310 11TH AVE E LLC | C408: LLC - Multi Member | D408: 531311 | E408: Residential Property Managers | F408: 53 | G408: 43101 | H408: 2018 | I408: 8 | J408: 6–10 years | K408: 0 | L408: 310 11TH AVE E | M408: SEATTLE | N408: WA | O408: 98102 | P408: 1 | Q408: 8442460759194 | R408: 6.0417947e+15
... A421: 345 CONSTRUCTION & FLOORING CO | B421: 345 CONSTRUCTION & FLOORING CO | C421: Corporation | D421: 238330 | E421: Flooring Contractors | F421: 23 | G421: 43963 | H421: 2020 | I421: 6 | J421: 6–10 years | K421: 0 | L421: 15405 MANOR WAY | M421: LYNNWOOD | N421: WA | O421: 98087 | P421: 0 | Q421: 8483460763589 | R421: 6.0420733e+15
A422: 345 HENRY DAVID DEMMERT | B422: HENRY DAVID DEMMERT | C422: Sole proprietorship | D422: 459999 | E422: All Other Miscellaneous Retailers | F422: 45 | G422: 45496 | H422: 2024 | I422: 2 | J422: 1–5 years | K422: 0 | L422: 19240 AURORA AVE N # 408 | M422: SEATTLE | N422: WA | O422: 98133 | P422: 1 | Q422: 8773880794176
A423: 346 N 77TH LLC | B423: 346 N 77TH LLC | C423: LLC - Multi Member | D423: 531110 | E423: Lessors of Residential Buildings and Dwellings | F423: 53 | G423: 45474 | H423: 2024 | I423: 2 | J423: 1–5 years | K423: 0 | L423: 346 N 77TH ST # B | M423: SEATTLE | N423: WA | O423: 98103 | P423: 1 | Q423: 8766310793382 | R423: 6.0554538e+15
A424: 350 SEATTLE | B424: 350 SEATTLE | C424: Association | D424: 813312 | E424: Environment, Conservation and Wildlife Organizations | F424: 81 | G424: 42095 | H424: 2015 | I424: 11 | J424: 11–20 years | K424: 0 | L424: 600 1ST AVE | M424: SEATTLE | N424: WA | O424: 98104 | P424: 1 | Q424: 7913530703970 | R424: 6.0334664e+15
A425: 3502 STREET LLC | B425: 3502 STREET LLC | C425: LLC - Multi Member | D425: 531110 | E425: Lessors of Residential Buildings and Dwellings | F425: 53 | G425: 45153 | H425: 2023 | I425: 2 | J425: 1–5 years | K425: 0 | L425: 3502 S DAWSON ST | M425: SEATTLE | N425: WA | O425: 98118 | P425: 1 | Q425: 8703550786695 | R425: 6.0467591e+15
A426: 35TH AVE HARVEST LLC | B426: GH PASTA AND PIZZA | C426: LLC - Single Member | D426: 722511 | E426: Full-Service Restaurants | F426: 72 | G426: 45248 | H426: 2023 | I426: 2 | J426: 1–5 years | K426: 0 | L426: 7500 35TH AVE SW | M426: SEATTLE | N426: WA | O426: 98126 | P426: 1 | Q426: 8736240790184 | R426: 6.0511812e+15
A427: 35TH AVENUE CHIROPRACTIC PLLC | B427: 35TH AVENUE CHIROPRACTIC PLLC | C427: Professional Association | D427: 621310 | E427: Offices of Chiropractors | F427: 62 | G427: 38961 | H427: 2006 | I427: 19 | J427: 11–20 years | K427: 0 | L427: 9455 35TH AVE SW | M427: SEATTLE | N427: WA | O427: 98126 | P427: 1 | Q427: 5901790597233 | R427: 6.0263244e+15
A428: 35TH NORTH INC | B428: 35TH NORTH INC | C428: Corporation | D428: 459999 | E428: All Other Miscellaneous Retailers | F428: 45 | G428: 37712 | H428: 2003 | I428: 23 | J428: More than 20 years | K428: 0 | L428: 1100 E PIKE ST | M428: SEATTLE | N428: WA | O428: 98122 | P428: 1 | Q428: 5608980565907 | R428: 6.0228051e+15
A429: 360 CONNECTIONS INTERNATIONAL LLC | B429: 360 CONNECTIONS | C429: LLC - Multi Member | D429: 541990 | E429: All Other Professional, Scientific, and Technical Services | F429: 54 | G429: 40422 | H429: 2010 | I429: 15 | J429: 11–20 years | K429: 0 | L429: 9020 28TH AVE NW | M429: SEATTLE | N429: WA | O429: 98117 | P429: 1 | Q429: 7304450639885 | R429: 6.0297004e+15
A430: 360 DEGREES MODERN LLC | B430: 360 DEGREES MODERN LLC | C430: LLC - Multi Member | D430: 531390 | E430: Other Activities Related to Real Estate | F430: 53 | G430: 42235 | H430: 2015 | I430: 10 | J430: 6–10 years | K430: 0 | L430: 3213 W WHEELER ST | M430: SEATTLE | N430: WA | O430: 98199 | P430: 1 | Q430: 7908220703418 | R430: 6.0353405e+15
A431: 360 OSTEOPATHY PLLC | B431: 360 OSTEOPATHY | C431: LLC - Single Member | D431: 541990 | E431: All Other Professional, Scientific, and Technical Services | F431: 54 | G431: 44105 | H431: 2020 | I431: 5 | J431: 1–5 years | K431: 0 | L431: 464 12TH AVE # 203 | M431: SEATTLE | N431: WA | O431: 98122 | P431: 1 | Q431: 8511950766598 | R431: 6.0461958e+15
A432: 360 PACIFIC REAL ESTATE LLC | B432: 360 PACIFIC REAL ESTATE | C432: Other | D432: 522310 | E432: Mortgage and Nonmortgage Loan Brokers | F432: 52 | G432: 43101 | H432: 2018 | I432: 8 | J432: 6–10 years | K432: 0 | L432: 2817 NE 55TH ST # C | M432: SEATTLE | N432: WA | O432: 98105 | P432: 1 | Q432: 8185280732221 | R432: 6.0420273e+15
A433: 360 SOCIAL IMPACT STUDIOS | B433: 360 SOCIAL IMPACT STUDIOS | C433: Non Profit Corporation | D433: 611430 | E433: Professional and Management Development Training | F433: 61 | G433: 45079 | H433: 2023 | I433: 3 | J433: 1–5 years | K433: 0 | L433: 3027 NE 120TH ST | M433: SEATTLE | N433: WA | O433: 98125 | P433: 1 | Q433: 8738860790450 | R433: 6.0497174e+15
A434: 3601 GROUP INC | B434: 3601 GROUP INC | C434: Corporation | D434: 541219 | E434: Other Accounting Services | F434: 54 | G434: 43556 | H434: 2019 | I434: 7 | J434: 6–10 years | K434: 0 | L434: 920 N 34TH ST # 200 | M434: SEATTLE | N434: WA | O434: 98103 | P434: 1 | Q434: 8343490748805 | R434: 6.0182664e+15
... A771: A & B FABRICATORS INC | B771: ALUMINUM & BRONZE FAB INC | C771: Corporation | D771: 332410 | E771: Power Boiler and Heat Exchanger Manufacturing | F771: 33 | G771: 38852 | H771: 2006 | I771: 20 | J771: 11–20 years | K771: 0 | L771: 231 D ST NW | M771: AUBURN | N771: WA | O771: 98001 | P771: 0 | Q771: 5901920597246 | R771: 6.0261633e+15
A772: A & D | B772: A & D | C772: Sole proprietorship | D772: 485310 | E772: Taxi and Ridesharing Services | F772: 48 | G772: 45188 | H772: 2023 | I772: 2 | J772: 1–5 years | K772: 0 | L772: 21211 81ST ST E | M772: BONNEY LAKE | N772: WA | O772: 98391 | P772: 0 | Q772: 8711400787535
A773: A & D CONSTRUCTION SERVICES INC | B773: A & D CONSTRUCTION SERVICES INC | C773: Corporation | D773: 236115 | E773: New Single-Family Housing Construction (except For-Sale Builders) | F773: 23 | G773: 39083 | H773: 2007 | I773: 19 | J773: 11–20 years | K773: 0 | L773: 14838 JAKE DR SE | M773: MONROE | N773: WA | O773: 98272 | P773: 0 | Q773: 7005640607927 | R773: 6.0267664e+15
A774: A & D CUSTOM CONCRETE LLC | B774: A & D CUSTOM CONCRETE LLC | C774: LLC - Multi Member | D774: 238990 | E774: All Other Specialty Trade Contractors | F774: 23 | G774: 42005 | H774: 2015 | I774: 11 | J774: 11–20 years | K774: 0 | L774: 3326 BICKFORD AVE STE D | M774: SNOHOMISH | N774: WA | O774: 98290 | P774: 0 | Q774: 7779660690010 | R774: 6.0345657e+15
A775: A & D ENTERPRISES INC | B775: EVERGREEN QUALITY LANDSCAPING | C775: Corporation | D775: 459999 | E775: All Other Miscellaneous Retailers | F775: 45 | G775: 40179 | H775: 2010 | I775: 16 | J775: 11–20 years | K775: 0 | L775: 2836 36TH AVE W | M775: SEATTLE | N775: WA | O775: 98199 | P775: 1 | Q775: 7324100641934 | R775: 6.0187737e+15
...

Sheet Ownership by Age
A3: License Count | B3: Business Age Group
A4: Ownership Type | B4: Less than 1 year | C4: 1–5 years | D4: 6–10 years | E4: 11–20 years | F4: More than 20 years | G4: Future start date | H4: Grand Total
A5: Association | B5: 1 | C5: 9 | D5: 17 | E5: 61 | F5: 21 | H5: 109
A6: Corporation | B6: 104 | C6: 478 | D6: 515 | E6: 831 | F6: 1168 | G6: 3 | H6: 3099
A7: General Partnership | B7: 3 | C7: 15 | D7: 9 | E7: 22 | F7: 38 | H7: 87
A8: Limited Liability Limited Ptrs | B8: 2 | C8: 45 | D8: 58 | E8: 3 | H8: 108
A9: Limited Liability Ptrs LLP | B9: 13 | C9: 37 | D9: 13 | E9: 11 | F9: 14 | H9: 88
A10: Limited Partnership | B10: 2 | C10: 7 | D10: 9 | E10: 2 | H10: 20
A11: LLC - Multi Member | B11: 147 | C11: 628 | D11: 526 | E11: 1070 | F11: 247 | G11: 4 | H11: 2622
A12: LLC - Single Member | B12: 545 | C12: 1839 | D12: 379 | E12: 21 | F12: 4 | G12: 9 | H12: 2797
A13: Municipality | B13: 1 | D13: 2 | E13: 1 | H13: 4
A14: Non Profit Corporation | B14: 14 | C14: 80 | D14: 30 | E14: 4 | F14: 8 | G14: 1 | H14: 137
A15: Other | B15: 1 | C15: 7 | D15: 380 | E15: 13 | F15: 34 | H15: 435
A16: Professional Association | B16: 1 | C16: 3 | D16: 22 | E16: 59 | F16: 13 | H16: 98
A17: Sole proprietorship | B17: 220 | C17: 807 | D17: 714 | E17: 803 | F17: 735 | G17: 4 | H17: 3283
A18: Trust | C18: 2 | H18: 2
A19: Joint Venture | C19: 3 | D19: 2 | H19: 5
A20: Tribal Government | C20: 1 | H20: 1
A21: LLC Limited Liability Co | D21: 2 | H21: 2
A22: Grand Total | B22: 1054 | C22: 3961 | D22: 2678 | E22: 2901 | F22: 2282 | G22: 21 | H22: 12897
